mbake/__init__.py
mbake/__main__.py
mbake/cli.py
mbake/completions.py
mbake/config.py
mbake/constants/__init__.py
mbake/constants/makefile_targets.py
mbake/constants/phony_targets.py
mbake/constants/shell_commands.py
mbake/core/__init__.py
mbake/core/formatter.py
mbake/core/rules/__init__.py
mbake/core/rules/assignment_spacing.py
mbake/core/rules/conditionals.py
mbake/core/rules/continuation.py
mbake/core/rules/duplicate_targets.py
mbake/core/rules/final_newline.py
mbake/core/rules/pattern_spacing.py
mbake/core/rules/phony.py
mbake/core/rules/recipe_validation.py
mbake/core/rules/rule_type_detection.py
mbake/core/rules/shell.py
mbake/core/rules/special_target_validation.py
mbake/core/rules/suffix_validation.py
mbake/core/rules/tabs.py
mbake/core/rules/target_spacing.py
mbake/core/rules/target_validation.py
mbake/core/rules/whitespace.py
mbake/plugins/base.py
mbake/utils/__init__.py
mbake/utils/format_disable.py
mbake/utils/line_utils.py
mbake/utils/pattern_utils.py
mbake/utils/version_utils.py
mbake-1.4.4.dist-info/METADATA
mbake-1.4.4.dist-info/WHEEL
mbake-1.4.4.dist-info/entry_points.txt
mbake-1.4.4.dist-info/licenses/LICENSE
mbake-1.4.4.dist-info/RECORD
