Metadata-Version: 2.4
Name: mbake
Version: 1.4.4
Summary: A Python-based Makefile formatter and linter
Project-URL: Homepage, https://github.com/EbodShojaei/bake
Project-URL: Documentation, https://github.com/EbodShojaei/bake#readme
Project-URL: Repository, https://github.com/EbodShojaei/bake
Project-URL: Bug Tracker, https://github.com/EbodShojaei/bake/issues
Project-URL: Changelog, https://github.com/EbodShojaei/bake/releases
Project-URL: Funding, https://github.com/sponsors/ebodshojaei
Author: mbake Contributors
License-Expression: MIT
License-File: LICENSE
Keywords: build-tools,formatter,linter,makefile
Classifier: Development Status :: 4 - Beta
Classifier: Environment :: Console
Classifier: Intended Audience :: Developers
Classifier: License :: OSI Approved :: MIT License
Classifier: Operating System :: OS Independent
Classifier: Programming Language :: Python :: 3
Classifier: Programming Language :: Python :: 3.9
Classifier: Programming Language :: Python :: 3.10
Classifier: Programming Language :: Python :: 3.11
Classifier: Programming Language :: Python :: 3.12
Classifier: Topic :: Software Development :: Build Tools
Classifier: Topic :: Software Development :: Quality Assurance
Classifier: Topic :: Text Processing :: Markup
Requires-Python: >=3.9
Requires-Dist: rich>=13.0.0
Requires-Dist: tomli>=1.2.1; python_version < '3.11'
Requires-Dist: typer>=0.9.0
Provides-Extra: dev
Requires-Dist: black>=23.0.0; extra == 'dev'
Requires-Dist: mypy>=1.0.0; extra == 'dev'
Requires-Dist: pre-commit>=3.0.0; extra == 'dev'
Requires-Dist: pytest-cov>=4.0.0; extra == 'dev'
Requires-Dist: pytest>=7.0.0; extra == 'dev'
Requires-Dist: ruff>=0.1.0; extra == 'dev'
Requires-Dist: tomli>=1.2.1; extra == 'dev'
